{
  "properties": {
    "activities": [
      {
        "type": "ExecutePipeline",
        "typeProperties": {
          "pipeline": {
            "referenceName": "3a89dfdf-9b50-8aeb-4096-5718328f0669",
            "type": "PipelineReference"
          },
          "parameters": {},
          "waitOnCompletion": true
        },
        "policy": {
          "secureInput": false
        },
        "name": "EmployeeLaborHours_Customer2_Month",
        "dependsOn": []
      },
      {
        "type": "ExecutePipeline",
        "typeProperties": {
          "pipeline": {
            "referenceName": "73408dcf-0f7a-9c80-47d3-88d89712a005",
            "type": "PipelineReference"
          },
          "parameters": {},
          "waitOnCompletion": true
        },
        "policy": {
          "secureInput": false
        },
        "name": "EmployeeLaborHours_Customer_Month",
        "dependsOn": []
      },
      {
        "type": "ExecutePipeline",
        "typeProperties": {
          "pipeline": {
            "referenceName": "1d2a7436-97de-9f44-434f-1aea91fc70c8",
            "type": "PipelineReference"
          },
          "parameters": {},
          "waitOnCompletion": true
        },
        "policy": {
          "secureInput": false
        },
        "name": "EmployeeLaborHours_Customer3_Month",
        "dependsOn": []
      },
      {
        "type": "ExecutePipeline",
        "typeProperties": {
          "pipeline": {
            "referenceName": "08fb0b46-7bcc-8da6-45ee-abbda85a777b",
            "type": "PipelineReference"
          },
          "parameters": {},
          "waitOnCompletion": true
        },
        "policy": {
          "secureInput": false
        },
        "name": "Sales_Associate_Mapping",
        "dependsOn": []
      },
      {
        "type": "ExecutePipeline",
        "typeProperties": {
          "pipeline": {
            "referenceName": "973a40f0-afc0-80da-4865-e7c1bda80404",
            "type": "PipelineReference"
          },
          "parameters": {},
          "waitOnCompletion": true
        },
        "policy": {
          "secureInput": false
        },
        "name": "stgCostMappingRank",
        "dependsOn": []
      },
      {
        "type": "ExecutePipeline",
        "typeProperties": {
          "pipeline": {
            "referenceName": "81fd5e01-5277-a126-41fb-f55627ac67be",
            "type": "PipelineReference"
          },
          "parameters": {},
          "waitOnCompletion": true
        },
        "policy": {
          "secureInput": false
        },
        "name": "stgSGAEmployeeDeparment",
        "dependsOn": []
      },
      {
        "type": "ExecutePipeline",
        "typeProperties": {
          "pipeline": {
            "referenceName": "465758a2-cb64-a2c4-4ae2-4dcd7695ccdf",
            "type": "PipelineReference"
          },
          "parameters": {},
          "waitOnCompletion": true
        },
        "policy": {
          "secureInput": false
        },
        "name": "stgGLAccountDepartmenLBCCostMapping",
        "dependsOn": []
      },
      {
        "type": "ExecutePipeline",
        "typeProperties": {
          "pipeline": {
            "referenceName": "5161b79f-a3f2-a51c-423b-98669436a8d6",
            "type": "PipelineReference"
          },
          "parameters": {},
          "waitOnCompletion": true
        },
        "policy": {
          "secureInput": false
        },
        "name": "stgLBCLaborActualCostMapping",
        "dependsOn": []
      },
      {
        "type": "ExecutePipeline",
        "typeProperties": {
          "pipeline": {
            "referenceName": "33579c67-a586-933e-4f00-b23e557a578b",
            "type": "PipelineReference"
          },
          "parameters": {},
          "waitOnCompletion": true
        },
        "policy": {
          "secureInput": false
        },
        "name": "TimeTrackingDetails",
        "dependsOn": []
      }
    ]
  }
}